pyFileFixity/__init__.py
pyFileFixity/easy_profiler.py
pyFileFixity/ecc_specification.txt
pyFileFixity/ecc_speedtest.py
pyFileFixity/filetamper.py
pyFileFixity/header_ecc.py
pyFileFixity/pff.py
pyFileFixity/repair_ecc.py
pyFileFixity/replication_repair.py
pyFileFixity/resiliency_tester.py
pyFileFixity/resiliency_tester_config.txt
pyFileFixity/rfigc.py
pyFileFixity/structural_adaptive_ecc.py
pyFileFixity/lib/__init__.py
pyFileFixity/lib/_compat.py
pyFileFixity/lib/aux_funcs.py
pyFileFixity/lib/eccman.py
pyFileFixity/lib/hasher.py
pyFileFixity/lib/md5py.py
pyFileFixity/lib/six.py
pyFileFixity/lib/tee.py
pyFileFixity/tests/__init__.py
pyFileFixity/tests/aux_tests.py
pyFileFixity/tests/test_aux_funcs.py
pyFileFixity/tests/test_eccman.py
pyFileFixity/tests/test_hasher.py
pyFileFixity/tests/test_header_ecc.py
pyFileFixity/tests/test_repair_ecc.py
pyFileFixity/tests/test_replication_repair.py
pyFileFixity/tests/test_resiliency_tester.py
pyFileFixity/tests/test_rfigc.py
pyFileFixity/tests/test_structural_adaptive_ecc.py
pyFileFixity/tests/test_tee.py
pyFileFixity/tests/files/alice.pdf
pyFileFixity/tests/files/testaa.txt
pyFileFixity/tests/files/tux.jpg
pyFileFixity/tests/files/tuxsmall.jpg
pyFileFixity/tests/files/Sub2/testsub2.txt
pyFileFixity/tests/files/sub/Snark.zip
pyFileFixity/tests/files/sub/testsub.txt
pyFileFixity/tests/results/resiliency_tester_config_easy.cfg
pyFileFixity/tests/results/resiliency_tester_config_hard.cfg
pyFileFixity/tests/results/test_header_ecc_test_algo.db
pyFileFixity/tests/results/test_header_ecc_test_dir.db
pyFileFixity/tests/results/test_header_ecc_test_one_file.db
pyFileFixity/tests/results/test_header_ecc_test_one_file_tamper.db
pyFileFixity/tests/results/test_repair_ecc_check.db
pyFileFixity/tests/results/test_repair_ecc_sa_check.db
pyFileFixity/tests/results/test_rfigc_test_dir.csv
pyFileFixity/tests/results/test_rfigc_test_error_file.log
pyFileFixity/tests/results/test_rfigc_test_one_file.csv
pyFileFixity-3.1.4.dist-info/LICENSE
pyFileFixity-3.1.4.dist-info/METADATA
pyFileFixity-3.1.4.dist-info/WHEEL
pyFileFixity-3.1.4.dist-info/entry_points.txt
pyFileFixity-3.1.4.dist-info/top_level.txt
pyFileFixity-3.1.4.dist-info/RECORD
