Metadata-Version: 2.1
Name: pyFileFixity
Version: 3.1.4
Summary: Helping file fixity (long term storage of data) via redundant error correcting codes and hash auditing.
Author-email: Stephen Karl Larroque <lrq3000@gmail.com>
Maintainer-email: Stephen Karl Larroque <lrq3000@gmail.com>
License: MIT License
Project-URL: Homepage, https://github.com/lrq3000/pyFileFixity
Project-URL: Documentation, https://github.com/lrq3000/pyFileFixity/blob/master/README.rst
Project-URL: Source, https://github.com/lrq3000/pyFileFixity
Project-URL: Tracker, https://github.com/lrq3000/pyFileFixity/issues
Project-URL: Download, https://github.com/lrq3000/pyFileFixity/releases
Keywords: file,repair,monitor,change,reed-solomon,error,correction,error correction,parity,parity files,parity bytes,data protection,data recovery,file protection,qr codes,qr code
Classifier: Development Status :: 5 - Production/Stable
Classifier: License :: OSI Approved :: MIT License
Classifier: Environment :: Console
Classifier: Operating System :: Microsoft :: Windows
Classifier: Operating System :: MacOS :: MacOS X
Classifier: Operating System :: POSIX :: Linux
Classifier: Programming Language :: Python
Classifier: Programming Language :: Python :: 3
Classifier: Programming Language :: Python :: 3.7
Classifier: Programming Language :: Python :: 3.8
Classifier: Programming Language :: Python :: 3.9
Classifier: Programming Language :: Python :: 3.10
Classifier: Programming Language :: Python :: 3.11
Classifier: Programming Language :: Python :: 3.12
Classifier: Programming Language :: Python :: Implementation :: PyPy
Classifier: Topic :: Software Development :: Libraries
Classifier: Topic :: Software Development :: Libraries :: Python Modules
Classifier: Topic :: System :: Archiving
Classifier: Topic :: System :: Archiving :: Backup
Classifier: Topic :: System :: Monitoring
Classifier: Topic :: System :: Recovery Tools
Classifier: Topic :: Utilities
Classifier: Intended Audience :: Developers
Classifier: Intended Audience :: End Users/Desktop
Classifier: Intended Audience :: Information Technology
Classifier: Intended Audience :: System Administrators
Requires-Python: >=3.7
License-File: LICENSE
Requires-Dist: pathlib2
Requires-Dist: argparse
Requires-Dist: sortedcontainers
Requires-Dist: tqdm
Requires-Dist: distance
Requires-Dist: reedsolo (>=2.0.0b1)
Requires-Dist: unireedsolomon
Provides-Extra: test
Requires-Dist: pytest ; extra == 'test'
Requires-Dist: pytest-cov ; extra == 'test'
Requires-Dist: py-make ; extra == 'test'
Provides-Extra: testmeta
Requires-Dist: build ; extra == 'testmeta'
Requires-Dist: twine ; extra == 'testmeta'
Requires-Dist: validate-pyproject ; extra == 'testmeta'
Requires-Dist: rstcheck ; extra == 'testmeta'
